micro_webview-1.0.1.dist-info/licenses/LICENCE
microwebview/__init__.py
micro_webview-1.0.1.dist-info/METADATA
micro_webview-1.0.1.dist-info/WHEEL
micro_webview-1.0.1.dist-info/top_level.txt
micro_webview-1.0.1.dist-info/RECORD
