Metadata-Version: 2.4
Name: Micro-WebView
Version: 1.0.1
Summary: Minimal Web View based on PyQtWebEngine
Author-email: Franek Kurzawa <frankox7@interia.pl>
License: Creative Commons Attribution-NoDerivatives 4.0 International License
Project-URL: Homepage, https://github.com/Franektoube/micro-webview
Requires-Python: >=3.7
License-File: LICENCE
Requires-Dist: PyQt5
Requires-Dist: PyQtWebEngine
Dynamic: license-file
